snapquery/__init__.py
snapquery/authorization.py
snapquery/basequeryview.py
snapquery/ceurws.py
snapquery/dblp.py
snapquery/error_filter.py
snapquery/execution.py
snapquery/github_access.py
snapquery/graph.py
snapquery/mwlogin.py
snapquery/namespace_stats_view.py
snapquery/orcid.py
snapquery/params_view.py
snapquery/person_selector.py
snapquery/pid.py
snapquery/pid_lookup.py
snapquery/prefix_merger.py
snapquery/qlever.py
snapquery/query_annotate.py
snapquery/query_parameterizer.py
snapquery/query_selector.py
snapquery/query_set_cmd.py
snapquery/query_set_tool.py
snapquery/query_set_tool_view.py
snapquery/scholia.py
snapquery/sib_sparql_examples.py
snapquery/snapquery_cmd.py
snapquery/snapquery_core.py
snapquery/snapquery_view.py
snapquery/snapquery_webserver.py
snapquery/sparql_analyzer.py
snapquery/stats_view.py
snapquery/version.py
snapquery/wd_page_query_extractor.py
snapquery/wd_short_url.py
snapquery/models/__init__.py
snapquery/models/person.py
snapquery/models/sparql_components.py
snapquery/resources/sparql_language.json
snapquery/samples/WikiProject_LSEThesisProject.wiki
snapquery/samples/ceur-ws.json
snapquery/samples/dblp.json
snapquery/samples/endpoints.yaml
snapquery/samples/endpoints_optional.yaml
snapquery/samples/federated-query-examples.json
snapquery/samples/graphs.yaml
snapquery/samples/meta_query.yaml
snapquery/samples/orkg.json
snapquery/samples/qlever.json
snapquery/samples/qlever_performance.json
snapquery/samples/query_stats.yaml
snapquery/samples/scholia.json
snapquery/samples/snapquery.json
snapquery/samples/wikidata-WikidataThesisToolkit.json
snapquery/samples/wikidata-WikidataThesisToolkitAlt.json
snapquery/samples/wikidata-examples.json
snapquery/samples/wikidata-short-urls.json
snapquery/samples/query-sets/yaml/ceur-ws.yaml
snapquery/samples/query-sets/yaml/dblp.yaml
snapquery/samples/query-sets/yaml/federated-query-examples.yaml
snapquery/samples/query-sets/yaml/hartig-eqs-2025-12-16.yaml
snapquery/samples/query-sets/yaml/orkg.yaml
snapquery-0.2.5.dist-info/METADATA
snapquery-0.2.5.dist-info/WHEEL
snapquery-0.2.5.dist-info/entry_points.txt
snapquery-0.2.5.dist-info/licenses/LICENSE
snapquery-0.2.5.dist-info/RECORD
