Metadata-Version: 2.4
Name: snapquery
Version: 0.2.5
Summary: Just Query wikidata and other SPARQL endpoints by query name - a frontend to Introduce Named Queries and Named Query Middleware to wikidata and other SPARQL endpoints 
Project-URL: Home, https://github.com/WolfgangFahl/snapquery
Project-URL: Documentation, https://wiki.bitplan.com/index.php/snapquery
Project-URL: Source, https://github.com/WolfgangFahl/snapquery
Author-email: Wolfgang Fahl <wf@WolfgangFahl.com>
Maintainer-email: Wolfgang Fahl <wf@WolfgangFahl.com>
License: Apache-2.0
License-File: LICENSE
Keywords: SPARQL,blazegraph,middleware,nicegui,qlever,query,wikidata
Classifier: Development Status :: 4 - Beta
Classifier: Environment :: Web Environment
Classifier: Intended Audience :: Developers
Classifier: Intended Audience :: Education
Classifier: Intended Audience :: Science/Research
Classifier: License :: OSI Approved :: Apache Software License
Classifier: Operating System :: OS Independent
Classifier: Programming Language :: Python :: 3 :: Only
Classifier: Programming Language :: Python :: 3.10
Classifier: Programming Language :: Python :: 3.11
Classifier: Programming Language :: Python :: 3.12
Classifier: Programming Language :: Python :: 3.13
Classifier: Topic :: Software Development :: User Interfaces
Requires-Python: >=3.10
Requires-Dist: mwoauth>=0.4.0
Requires-Dist: nameparser>=1.1.3
Requires-Dist: ngwidgets>=0.30.3
Requires-Dist: nicegui[plotly]==2.24.2
Requires-Dist: pandas>=2.3.3
Requires-Dist: py-3rdparty-mediawiki>=0.18.1
Requires-Dist: py-ez-wikidata>=0.3.2
Requires-Dist: pybasemkit>=0.1.6
Requires-Dist: pylodstorage>=0.18.6
Requires-Dist: pyopensourceprojects>=0.4.1
Requires-Dist: python-slugify>=8.0.4
Requires-Dist: ratelimit>=2.2.1
Requires-Dist: requests
Requires-Dist: tqdm>=4.66.4
Requires-Dist: wikitextparser
Provides-Extra: test
Requires-Dist: green; extra == 'test'
